Workbook

Sheet 📊 Dashboard
B2: 💼 FREELANCER INVOICE & TAX TRACKER · BuildWithGimi
B4: TOTAL INVOICED | C4: TOTAL PAID | D4: OUTSTANDING | E4: OVERDUE | F4: EXPENSES | G4: NET PROFIT
B5: =SUMIF('🧾 Invoices'!H:H,"*", '🧾 Invoices'!G:G) | C5: =SUMIF('🧾 Invoices'!H:H,"Paid",'🧾 Invoices'!G:G) | D5: =SUMIF('🧾 Invoices'!H:H,"Sent",'🧾 Invoices'!G:G) | E5: =SUMIF('🧾 Invoices'!H:H,"Overdue",'🧾 Invoices'!G:G) | F5: =SUM('💸 Expenses'!D:D) | G5: =C5-F5
B7: QUARTERLY BREAKDOWN
B8: QUARTER | C8: INVOICED | D8: PAID | E8: EXPENSES | F8: TAX EST (25%) | G8: NET
B9: Q1 (Jan–Mar) | C9: 0 | D9: 0 | E9: 0 | F9: =D9*0.25 | G9: =C9-D9-E9
B10: Q2 (Apr–Jun) | C10: 0 | D10: 0 | E10: 0 | F10: =D10*0.25 | G10: =C10-D10-E10
B11: Q3 (Jul–Sep) | C11: 0 | D11: 0 | E11: 0 | F11: =D11*0.25 | G11: =C11-D11-E11
B12: Q4 (Oct–Dec) | C12: 0 | D12: 0 | E12: 0 | F12: =D12*0.25 | G12: =C12-D12-E12
B14: 💡 HOW TO USE: Add invoices in '🧾 Invoices' · Add expenses in '💸 Expenses' · This dashboard updates automatically

Sheet 🧾 Invoices
A1: 🧾 INVOICES — BuildWithGimi Freelancer Tracker
A2: INV # | B2: CLIENT | C2: PROJECT | D2: DATE ISSUED | E2: DUE DATE | F2: CURRENCY | G2: AMOUNT | H2: STATUS | I2: PAID DATE | J2: NOTES
A3: INV-001 | B3: Acme Corp | C3: Website Redesign | D3: 2026-01-10 | E3: 2026-01-25 | F3: USD | G3: 2500 | H3: Paid | I3: 2026-01-22
A4: INV-002 | B4: Bright Media | C4: SEO Audit | D4: 2026-02-01 | E4: 2026-02-15 | F4: USD | G4: 800 | H4: Paid | I4: 2026-02-14
A5: INV-003 | B5: TechFlow Inc | C5: API Integration | D5: 2026-02-20 | E5: 2026-03-06 | F5: USD | G5: 1500 | H5: Overdue | J5: Client delayed
A6: INV-004 | B6: Nova StartUp | C6: Pitch Deck | D6: 2026-03-01 | E6: 2026-03-15 | F6: USD | G6: 650 | H6: Sent
A7: INV-005 | B7: Bright Media | C7: Monthly Retainer Mar | D7: 2026-03-01 | E7: 2026-03-15 | F7: USD | G7: 1200 | H7: Sent

Sheet 💸 Expenses
A1: 💸 EXPENSES — BuildWithGimi Freelancer Tracker
A2: DATE | B2: CATEGORY | C2: DESCRIPTION | D2: AMOUNT | E2: DEDUCTIBLE? | F2: RECEIPT | G2: NOTES
A3: 2026-01-05 | B3: Software | C3: Figma subscription | D3: 15 | E3: Yes | G3: Annual plan
A4: 2026-01-12 | B4: Software | C4: Adobe CC monthly | D4: 60 | E4: Yes
A5: 2026-02-03 | B5: Marketing | C5: LinkedIn Premium | D5: 30 | E5: Yes | G5: Lead gen
A6: 2026-02-15 | B6: Hardware | C6: USB-C Hub | D6: 45 | E6: Yes
A7: 2026-03-01 | B7: Education | C7: Online course - Notion | D7: 97 | E7: Yes | G7: Productivity
A8: 2026-03-10 | B8: Software | C8: Vercel Pro (if upgraded) | D8: 20 | E8: Yes | G8: Hosting

Sheet 🧮 Tax Estimator
B1: 🧮 TAX ESTIMATOR
B3: INCOME
B4: Total Invoiced | C4: ='🧾 Invoices'!G2
B5: Total Paid | C5: =SUMIF('🧾 Invoices'!H:H,"Paid",'🧾 Invoices'!G:G)
B6: Outstanding | C6: =SUMIF('🧾 Invoices'!H:H,"Sent",'🧾 Invoices'!G:G)
B8: DEDUCTIONS
B9: Total Deductible Exp. | C9: =SUMIF('💸 Expenses'!E:E,"Yes",'💸 Expenses'!D:D)
B10: Partial Deductions (50%) | C10: =SUMIF('💸 Expenses'!E:E,"Partial",'💸 Expenses'!D:D)*0.5
B11: Total Deductions | C11: =C9+C10
B13: TAX CALCULATION
B14: Taxable Income | C14: =C5-C11
B15: Tax Rate (%) | C15: 0.25
B16: Estimated Tax | C16: =C14*C15
B17: Net After Tax | C17: =C14-C16
B19: ⚠️ This is an estimate only. Consult a local tax advisor for exact obligations.

Sheet 👥 Clients
A1: 👥 CLIENTS — BuildWithGimi Freelancer Tracker
A2: CLIENT NAME | B2: CONTACT | C2: EMAIL | D2: PHONE | E2: CURRENCY | F2: TOTAL BILLED | G2: STATUS | H2: NOTES
A3: Acme Corp | B3: John Doe | C3: john@acme.com | D3: +1-555-0100 | E3: USD | F3: 2500 | G3: Active | H3: Top client
A4: Bright Media | B4: Sara Lee | C4: sara@bright.co | D4: +1-555-0200 | E4: USD | F4: 2000 | G4: Active | H4: Monthly retainer
A5: TechFlow Inc | B5: Mike Stern | C5: mike@techflow.io | D5: +1-555-0300 | E5: USD | F5: 1500 | G5: Overdue | H5: Net 30 terms
A6: Nova StartUp | B6: Ana Popa | C6: ana@nova.ro | D6: +40-720-000 | E6: USD | F6: 650 | G6: Active | H6: RO client
